odoo8_addon_payment_alipay-8.0.2.0.2.99.dev7-py2.7-nspkg.pth
odoo8_addon_payment_alipay-8.0.2.0.2.99.dev7.dist-info/DESCRIPTION.rst
odoo8_addon_payment_alipay-8.0.2.0.2.99.dev7.dist-info/METADATA
odoo8_addon_payment_alipay-8.0.2.0.2.99.dev7.dist-info/RECORD
odoo8_addon_payment_alipay-8.0.2.0.2.99.dev7.dist-info/WHEEL
odoo8_addon_payment_alipay-8.0.2.0.2.99.dev7.dist-info/metadata.json
odoo8_addon_payment_alipay-8.0.2.0.2.99.dev7.dist-info/namespace_packages.txt
odoo8_addon_payment_alipay-8.0.2.0.2.99.dev7.dist-info/top_level.txt
odoo_addons/payment_alipay/README.rst
odoo_addons/payment_alipay/__init__.py
odoo_addons/payment_alipay/__openerp__.py
odoo_addons/payment_alipay/controllers/__init__.py
odoo_addons/payment_alipay/controllers/main.py
odoo_addons/payment_alipay/data/alipay.xml
odoo_addons/payment_alipay/edi/__init__.py
odoo_addons/payment_alipay/edi/account_invoice.py
odoo_addons/payment_alipay/edi/sale_order.py
odoo_addons/payment_alipay/edi/sale_order_action_data.xml
odoo_addons/payment_alipay/i18n/zh_CN.po
odoo_addons/payment_alipay/models/__init__.py
odoo_addons/payment_alipay/models/payment_acquirer.py
odoo_addons/payment_alipay/models/payment_transaction.py
odoo_addons/payment_alipay/security/ir.model.access.csv
odoo_addons/payment_alipay/static/description/icon.png
odoo_addons/payment_alipay/static/img/btn_alipay_lg.gif
odoo_addons/payment_alipay/static/src/img/alipay_icon.png
odoo_addons/payment_alipay/static/src/img/alipay_icon_1111.png
odoo_addons/payment_alipay/tests/__init__.py
odoo_addons/payment_alipay/tests/test_main.py
odoo_addons/payment_alipay/tests/test_payment_acquirer.py
odoo_addons/payment_alipay/tests/test_payment_method.py
odoo_addons/payment_alipay/tests/test_payment_transaction.py
odoo_addons/payment_alipay/tests/test_sale_order.py
odoo_addons/payment_alipay/views/alipay.xml
odoo_addons/payment_alipay/views/payment_acquirer.xml
