Metadata-Version: 2.0
Name: odoo8-addon-payment-alipay
Version: 8.0.2.0.2.99.dev7
Summary: Payment Acquirer: Alipay Implementation
Home-page: UNKNOWN
Author: Elico-Corp, Odoo Community Association (OCA)
Author-email: support@odoo-community.org
License: UNKNOWN
Platform: UNKNOWN
Classifier: Programming Language :: Python :: 2.7
Classifier: Framework :: Odoo
Requires-Dist: odoo (<9.0a,>=8.0a)
